{
	"model": "dining_facilities",
	"data": [
		{
			"amenities": {
				"set": [
					"24_hours",
					"accessible_restaurant",
					"bar",
					"buffet",
					"cafe"
				]
			},
			"cuisines": { "set": ["3", "6"] },
			"dietary_options": { "set": ["1"] },
			"group_dining_policy": "Bring your friends!",
			"max_seating_capacity": 150,
			"max_standing_capacity": 20,
			"meals_served": { "set": ["1", "2", "4", "3"] },
			"menu_link": "http://4thstreetmarket.com/menu",
			"price": { "set": "2" },
			"private_dining_capacity": 25,
			"property_id": "1",
			"reservation_link": "http://4thstreetmarket.com"
		},
		{
			"amenities": {
				"set": [
					"accessible_restaurant",
					"bar",
					"champagne_service",
					"smoke_free_property",
					"lounge"
				]
			},
			"cuisines": { "set": ["3"] },
			"meals_served": { "set": ["3", "4"] },
			"dining_types": { "set": ["1", "5"] },
			"menu_link": "https://www.theclubatstarrpass.com/Files/Library/CBCOMENU1_12JSH2.PDF",
			"price": { "set": "2" },
			"property_id": "7",
			"reservation_link": "https://www.opentable.com/r/catalina-sports-bar-tucson"
		}
	]
}
